TRS/Globals.py
TRS/Lib.py
TRS/LibPeakCaller.py
TRS/MergedPeakCaller.py
TRS/__init__.py
TRS/DAL/__init__.py
TRS/DAL/BAM/BamReader.py
TRS/DAL/BAM/__init__.py
TRS/DAL/Track/ChrCounts.py
TRS/DAL/Track/Counts.py
TRS/DAL/Track/Coverage.py
TRS/DAL/Track/__init__.py
TRSalgorithm-0.0.1.dist-info/LICENSE
TRSalgorithm-0.0.1.dist-info/METADATA
TRSalgorithm-0.0.1.dist-info/WHEEL
TRSalgorithm-0.0.1.dist-info/entry_points.txt
TRSalgorithm-0.0.1.dist-info/top_level.txt
TRSalgorithm-0.0.1.dist-info/RECORD
