Metadata-Version: 2.1
Name: TRSalgorithm
Version: 0.0.1
Summary: Determining 3' termini of transcripts from RNAtag-seq data in bacteria
Author-email: Amir Bar <amir.bar@mail.huji.ac.il>
Project-URL: Homepage, https://github.com/amirbarHUJI/TRS
Project-URL: Bug Tracker, https://github.com/amirbarHUJI/TRS/issues
Classifier: Programming Language :: Python :: 3
Classifier: License :: OSI Approved :: MIT License
Classifier: Operating System :: OS Independent
Classifier: Topic :: Scientific/Engineering :: Bio-Informatics
Requires-Python: >=3.7
License-File: LICENSE
Requires-Dist: scipy (>=1.7.3)
Requires-Dist: numpy (>=1.21.6)
Requires-Dist: pysam (>=0.20.0)
Requires-Dist: pandas (>=1.3.5)
Requires-Dist: statsmodels (>=0.13.5)
Requires-Dist: pyaml
Requires-Dist: intervaltree
